{
	"s23_l_bwbg2a": [
		{
			"duration": 0.07,
			"offset": 0,
			"phone": "SIL_S"
		},
		{
			"duration": 0.15,
			"offset": 0.07,
			"phone": "b_B"
		},
		{
			"duration": 0.13,
			"offset": 0.22,
			"phone": "ih_I"
		},
		{
			"duration": 0.06,
			"offset": 0.35,
			"phone": "n_E"
		},
		{
			"duration": 0.09,
			"offset": 0.41,
			"phone": "w_B"
		},
		{
			"duration": 0.19,
			"offset": 0.5,
			"phone": "ay_I"
		},
		{
			"duration": 0.12,
			"offset": 0.69,
			"phone": "t_E"
		},
		{
			"duration": 0.06,
			"offset": 0.81,
			"phone": "SIL"
		},
		{
			"duration": 0.14,
			"offset": 0.87,
			"phone": "b_B"
		},
		{
			"duration": 0.13,
			"offset": 1.01,
			"phone": "ay_E"
		},
		{
			"duration": 0.03,
			"offset": 1.14,
			"phone": "SIL"
		},
		{
			"duration": 0.19,
			"offset": 1.17,
			"phone": "jh_B"
		},
		{
			"duration": 0.15,
			"offset": 1.36,
			"phone": "iy_E"
		},
		{
			"duration": 0.21,
			"offset": 1.51,
			"phone": "t_B"
		},
		{
			"duration": 0.19,
			"offset": 1.72,
			"phone": "uw_E"
		},
		{
			"duration": 0.11,
			"offset": 1.91,
			"phone": "ax_B"
		},
		{
			"duration": 0.06,
			"offset": 2.02,
			"phone": "g_I"
		},
		{
			"duration": 0.19,
			"offset": 2.08,
			"phone": "eh_I"
		},
		{
			"duration": 0.25,
			"offset": 2.27,
			"phone": "n_E"
		},
		{
			"duration": 0.14,
			"offset": 2.52,
			"phone": "SIL_S"
		}
	]
}
