{
	"s23_p_swbj4s": [
		{
			"duration": 0.03,
			"offset": 0,
			"phone": "SIL_S"
		},
		{
			"duration": 0.13,
			"offset": 0.03,
			"phone": "s_B"
		},
		{
			"duration": 0.11,
			"offset": 0.16,
			"phone": "eh_I"
		},
		{
			"duration": 0.15,
			"offset": 0.27,
			"phone": "t_E"
		},
		{
			"duration": 0.14,
			"offset": 0.42,
			"phone": "w_B"
		},
		{
			"duration": 0.15,
			"offset": 0.56,
			"phone": "ay_I"
		},
		{
			"duration": 0.14,
			"offset": 0.71,
			"phone": "t_E"
		},
		{
			"duration": 0.06,
			"offset": 0.85,
			"phone": "SIL"
		},
		{
			"duration": 0.06,
			"offset": 0.91,
			"phone": "b_B"
		},
		{
			"duration": 0.22,
			"offset": 0.97,
			"phone": "ay_E"
		},
		{
			"duration": 0.06,
			"offset": 1.19,
			"phone": "SIL"
		},
		{
			"duration": 0.16,
			"offset": 1.25,
			"phone": "jh_B"
		},
		{
			"duration": 0.07,
			"offset": 1.41,
			"phone": "ax_I"
		},
		{
			"duration": 0.13,
			"offset": 1.48,
			"phone": "iy_E"
		},
		{
			"duration": 0.03,
			"offset": 1.61,
			"phone": "SIL"
		},
		{
			"duration": 0.2,
			"offset": 1.64,
			"phone": "f_B"
		},
		{
			"duration": 0.22,
			"offset": 1.84,
			"phone": "ao_E"
		},
		{
			"duration": 0.23,
			"offset": 2.06,
			"phone": "s_B"
		},
		{
			"duration": 0.16,
			"offset": 2.29,
			"phone": "uw_I"
		},
		{
			"duration": 0.15,
			"offset": 2.45,
			"phone": "n_E"
		},
		{
			"duration": 0.09,
			"offset": 2.6,
			"phone": "SIL_S"
		}
	]
}
