{
	"s31_p_bgwdzn": [
		{
			"duration": 0.08,
			"offset": 0,
			"phone": "SIL_S"
		},
		{
			"duration": 0.1,
			"offset": 0.08,
			"phone": "b_B"
		},
		{
			"duration": 0.05,
			"offset": 0.18,
			"phone": "ih_I"
		},
		{
			"duration": 0.07,
			"offset": 0.23,
			"phone": "n_E"
		},
		{
			"duration": 0.05,
			"offset": 0.3,
			"phone": "g_B"
		},
		{
			"duration": 0.12,
			"offset": 0.35,
			"phone": "r_I"
		},
		{
			"duration": 0.15,
			"offset": 0.47,
			"phone": "iy_I"
		},
		{
			"duration": 0.05,
			"offset": 0.62,
			"phone": "n_E"
		},
		{
			"duration": 0.1,
			"offset": 0.67,
			"phone": "w_B"
		},
		{
			"duration": 0.04,
			"offset": 0.77,
			"phone": "ih_I"
		},
		{
			"duration": 0.13,
			"offset": 0.81,
			"phone": "dh_E"
		},
		{
			"duration": 0.07,
			"offset": 0.94,
			"phone": "SIL"
		},
		{
			"duration": 0.07,
			"offset": 1.01,
			"phone": "d_B"
		},
		{
			"duration": 0.17,
			"offset": 1.08,
			"phone": "iy_E"
		},
		{
			"duration": 0.1,
			"offset": 1.25,
			"phone": "z_B"
		},
		{
			"duration": 0.21,
			"offset": 1.35,
			"phone": "ia_I"
		},
		{
			"duration": 0.07,
			"offset": 1.56,
			"phone": "r_I"
		},
		{
			"duration": 0.11,
			"offset": 1.63,
			"phone": "ow_E"
		},
		{
			"duration": 0.16,
			"offset": 1.74,
			"phone": "n_B"
		},
		{
			"duration": 0.35,
			"offset": 1.9,
			"phone": "aw_E"
		},
		{
			"duration": 0.08,
			"offset": 2.25,
			"phone": "SIL_S"
		}
	]
}
