{
	"s47_p_brib9n": [
		{
			"duration": 0.05,
			"offset": 0,
			"phone": "SIL_S"
		},
		{
			"duration": 0.08,
			"offset": 0.05,
			"phone": "b_B"
		},
		{
			"duration": 0.03,
			"offset": 0.13,
			"phone": "ih_I"
		},
		{
			"duration": 0.04,
			"offset": 0.16,
			"phone": "n_E"
		},
		{
			"duration": 0.05,
			"offset": 0.2,
			"phone": "r_B"
		},
		{
			"duration": 0.08,
			"offset": 0.25,
			"phone": "eh_I"
		},
		{
			"duration": 0.06,
			"offset": 0.33,
			"phone": "d_E"
		},
		{
			"duration": 0.05,
			"offset": 0.39,
			"phone": "ih_B"
		},
		{
			"duration": 0.09,
			"offset": 0.44,
			"phone": "n_E"
		},
		{
			"duration": 0.03,
			"offset": 0.53,
			"phone": "SIL"
		},
		{
			"duration": 0.05,
			"offset": 0.56,
			"phone": "b_B"
		},
		{
			"duration": 0.06,
			"offset": 0.61,
			"phone": "iy_E"
		},
		{
			"duration": 0.1,
			"offset": 0.67,
			"phone": "n_B"
		},
		{
			"duration": 0.12,
			"offset": 0.77,
			"phone": "ay_I"
		},
		{
			"duration": 0.04,
			"offset": 0.89,
			"phone": "n_E"
		},
		{
			"duration": 0.08,
			"offset": 0.93,
			"phone": "n_B"
		},
		{
			"duration": 0.19,
			"offset": 1.01,
			"phone": "aw_E"
		},
		{
			"duration": 0.11,
			"offset": 1.2,
			"phone": "SIL_S"
		}
	]
}
