{
	"s49_l_sgah9p": [
		{
			"duration": 0.03,
			"offset": 0,
			"phone": "SIL_S"
		},
		{
			"duration": 0.03,
			"offset": 0.03,
			"phone": "s_B"
		},
		{
			"duration": 0.1,
			"offset": 0.06,
			"phone": "eh_I"
		},
		{
			"duration": 0.09,
			"offset": 0.16,
			"phone": "t_E"
		},
		{
			"duration": 0.06,
			"offset": 0.25,
			"phone": "g_B"
		},
		{
			"duration": 0.16,
			"offset": 0.31,
			"phone": "r_I"
		},
		{
			"duration": 0.15,
			"offset": 0.47,
			"phone": "iy_I"
		},
		{
			"duration": 0.15,
			"offset": 0.62,
			"phone": "n_E"
		},
		{
			"duration": 0.2,
			"offset": 0.77,
			"phone": "ae_B"
		},
		{
			"duration": 0.15,
			"offset": 0.97,
			"phone": "t_E"
		},
		{
			"duration": 0.25,
			"offset": 1.12,
			"phone": "ey_B"
		},
		{
			"duration": 0.16,
			"offset": 1.37,
			"phone": "ch_E"
		},
		{
			"duration": 0.11,
			"offset": 1.53,
			"phone": "n_B"
		},
		{
			"duration": 0.16,
			"offset": 1.64,
			"phone": "ay_I"
		},
		{
			"duration": 0.16,
			"offset": 1.8,
			"phone": "n_E"
		},
		{
			"duration": 0.06,
			"offset": 1.96,
			"phone": "SIL"
		},
		{
			"duration": 0.07,
			"offset": 2.02,
			"phone": "p_B"
		},
		{
			"duration": 0.06,
			"offset": 2.09,
			"phone": "l_I"
		},
		{
			"duration": 0.19,
			"offset": 2.15,
			"phone": "iy_I"
		},
		{
			"duration": 0.26,
			"offset": 2.34,
			"phone": "z_E"
		},
		{
			"duration": 0.03,
			"offset": 2.6,
			"phone": "SIL_S"
		}
	]
}
