{
	"s52_p_brwp3s": [
		{
			"duration": 0.05,
			"offset": 0,
			"phone": "SIL_S"
		},
		{
			"duration": 0.08,
			"offset": 0.05,
			"phone": "b_B"
		},
		{
			"duration": 0.04,
			"offset": 0.13,
			"phone": "ih_I"
		},
		{
			"duration": 0.17,
			"offset": 0.17,
			"phone": "n_E"
		},
		{
			"duration": 0.05,
			"offset": 0.34,
			"phone": "r_B"
		},
		{
			"duration": 0.13,
			"offset": 0.39,
			"phone": "eh_I"
		},
		{
			"duration": 0.14,
			"offset": 0.52,
			"phone": "d_E"
		},
		{
			"duration": 0.03,
			"offset": 0.66,
			"phone": "SIL"
		},
		{
			"duration": 0.14,
			"offset": 0.69,
			"phone": "w_B"
		},
		{
			"duration": 0.14,
			"offset": 0.83,
			"phone": "ih_I"
		},
		{
			"duration": 0.13,
			"offset": 0.97,
			"phone": "dh_E"
		},
		{
			"duration": 0.25,
			"offset": 1.1,
			"phone": "SIL"
		},
		{
			"duration": 0.09,
			"offset": 1.35,
			"phone": "p_B"
		},
		{
			"duration": 0.14,
			"offset": 1.44,
			"phone": "iy_E"
		},
		{
			"duration": 0.12,
			"offset": 1.58,
			"phone": "th_B"
		},
		{
			"duration": 0.07,
			"offset": 1.7,
			"phone": "r_I"
		},
		{
			"duration": 0.17,
			"offset": 1.77,
			"phone": "iy_E"
		},
		{
			"duration": 0.17,
			"offset": 1.94,
			"phone": "s_B"
		},
		{
			"duration": 0.18,
			"offset": 2.11,
			"phone": "uw_I"
		},
		{
			"duration": 0.17,
			"offset": 2.29,
			"phone": "n_E"
		},
		{
			"duration": 0.11,
			"offset": 2.46,
			"phone": "SIL_S"
		}
	]
}
