{
	"s54_l_bwixza": [
		{
			"duration": 0.05,
			"offset": 0,
			"phone": "SIL_S"
		},
		{
			"duration": 0.06,
			"offset": 0.05,
			"phone": "b_B"
		},
		{
			"duration": 0.04,
			"offset": 0.11,
			"phone": "ih_I"
		},
		{
			"duration": 0.07,
			"offset": 0.15,
			"phone": "n_E"
		},
		{
			"duration": 0.06,
			"offset": 0.22,
			"phone": "w_B"
		},
		{
			"duration": 0.13,
			"offset": 0.28,
			"phone": "ay_I"
		},
		{
			"duration": 0.12,
			"offset": 0.41,
			"phone": "t_E"
		},
		{
			"duration": 0.03,
			"offset": 0.53,
			"phone": "ih_B"
		},
		{
			"duration": 0.05,
			"offset": 0.56,
			"phone": "n_E"
		},
		{
			"duration": 0.03,
			"offset": 0.61,
			"phone": "SIL"
		},
		{
			"duration": 0.1,
			"offset": 0.64,
			"phone": "eh_B"
		},
		{
			"duration": 0.12,
			"offset": 0.74,
			"phone": "k_I"
		},
		{
			"duration": 0.1,
			"offset": 0.86,
			"phone": "s_E"
		},
		{
			"duration": 0.27,
			"offset": 0.96,
			"phone": "ow_S"
		},
		{
			"duration": 0.05,
			"offset": 1.23,
			"phone": "ax_B"
		},
		{
			"duration": 0.04,
			"offset": 1.28,
			"phone": "g_I"
		},
		{
			"duration": 0.07,
			"offset": 1.32,
			"phone": "eh_I"
		},
		{
			"duration": 0.12,
			"offset": 1.39,
			"phone": "n_E"
		},
		{
			"duration": 0.13,
			"offset": 1.51,
			"phone": "SIL_S"
		}
	]
}
